{
  "placeholderImages": [
    {
      "id": "camry-xse",
      "description": "Un sedán rojo moderno en una ciudad.",
      "imageUrl": "https://images.unsplash.com/photo-1729080562616-3b9758cae13e?crop=entropy&cs=tinysrgb&fit=max&fm=jpg&ixid=M3w3NDE5ODJ8MHwxfHNlYXJjaHwxfHxzZWRhbiUyMHJvam98ZW58MHx8fHwxNzYzMDgyOTA1fDA&ixlib=rb-4.1.0&q=80&w=1080",
      "imageHint": "sedan rojo",
      "width": 800,
      "height": 600
    },
    {
      "id": "f150-lariat",
      "description": "Una camioneta Ford azul en un entorno de trabajo.",
      "imageUrl": "https://images.unsplash.com/photo-1681351623077-e4cc438f0548?crop=entropy&cs=tinysrgb&fit=max&fm=jpg&ixid=M3w3NDE5ODJ8MHwxfHNlYXJjaHwyfHxjYW1pb25ldGElMjBhenVsfGVufDB8fHx8MTc2MzA4MjkwNXww&ixlib=rb-4.1.0&q=80&w=1080",
      "imageHint": "camioneta azul",
      "width": 800,
      "height": 600
    },
    {
      "id": "model-3-lr",
      "description": "Un Tesla blanco cargándose en una estación de carga.",
      "imageUrl": "https://images.unsplash.com/photo-1643475246169-dd57253b646a?crop=entropy&cs=tinysrgb&fit=max&fm=jpg&ixid=M3w3NDE5ODJ8MHwxfHNlYXJjaHwzfHx0ZXNsYSUyMGJsYW5jb3xlbnwwfHx8fDE3NjMwODI5MDV8MA&ixlib=rb-4.1.0&q=80&w=1080",
      "imageHint": "tesla blanco",
      "width": 800,
      "height": 600
    },
    {
      "id": "crv-touring",
      "description": "Un SUV gris en un camino rural.",
      "imageUrl": "https://images.unsplash.com/photo-1733759845506-e197dbc047c8?crop=entropy&cs=tinysrgb&fit=max&fm=jpg&ixid=M3w3NDE5ODJ8MHwxfHNlYXJjaHw0fHxzdXYlMjBncmlzfGVufDB8fHx8MTc2MzA4MjkwNXww&ixlib=rb-4.1.0&q=80&w=1080",
      "imageHint": "suv gris",
      "width": 800,
      "height": 600
    },
    {
      "id": "911-gt3",
      "description": "Un Porsche amarillo en una pista de carreras.",
      "imageUrl": "https://images.unsplash.com/photo-1711998034162-380d2c7a5875?crop=entropy&cs=tinysrgb&fit=max&fm=jpg&ixid=M3w3NDE5ODJ8MHwxfHNlYXJjaHw2fHxwb3JzY2hlJTIwYW1hcmlsbG98ZW58MHx8fHwxNzYzMDgyOTA1fDA&ixlib=rb-4.1.0&q=80&w=1080",
      "imageHint": "porsche amarillo",
      "width": 800,
      "height": 600
    },
    {
      "id": "ioniq5-limited",
      "description": "Un SUV eléctrico plateado con diseño moderno.",
      "imageUrl": "https://picsum.photos/seed/ioniq5-limited/800/600",
      "imageHint": "suv electrico",
      "width": 800,
      "height": 600
    },
    {
      "id": "wrangler-rubicon",
      "description": "Un Jeep verde en un terreno rocoso.",
      "imageUrl": "https://images.unsplash.com/photo-1556821043-11c39c6e69cf?crop=entropy&cs=tinysrgb&fit=max&fm=jpg&ixid=M3w3NDE5ODJ8MHwxfHNlYXJjaHwxfHxqZWVwJTIwdmVyZGV8ZW58MHx8fHwxNzYzMDgyOTA1fDA&ixlib=rb-4.1.0&q=80&w=1080",
      "imageHint": "jeep verde",
      "width": 800,
      "height": 600
    },
    {
      "id": "bmw-330i",
      "description": "Un sedán BMW negro de lujo en una calle de la ciudad por la noche.",
      "imageUrl": "https://images.unsplash.com/photo-1563826773-1e2b4b2cde42?crop=entropy&cs=tinysrgb&fit=max&fm=jpg&ixid=M3w3NDE5ODJ8MHwxfHNlYXJjaHwyfHxibXclMjBuZWdyb3xlbnwwfHx8fDE3NjMwODI5MDV8MA&ixlib=rb-4.1.0&q=80&w=1080",
      "imageHint": "bmw negro",
      "width": 800,
      "height": 600
    },
    {
      "id": "prestige-x10",
      "description": "Un sedán de lujo en una ciudad de noche.",
      "imageUrl": "https://picsum.photos/seed/prestige-x10/800/600",
      "imageHint": "sedán de lujo",
      "width": 800,
      "height": 600
    },
    {
      "id": "aurora-gt-red",
      "description": "Un auto deportivo rojo en una carretera sinuosa.",
      "imageUrl": "https://images.unsplash.com/photo-1678079824721-ff86eeac5065?crop=entropy&cs=tinysrgb&fit=max&fm=jpg&ixid=M3w3NDE5ODJ8MHwxfHNlYXJjaHw0fHxhdXRvJTIwZGVwb3J0aXZvJTIwcm9qb3xlbnwwfHx8fDE3NjI4OTQ0MjR8MA&ixlib=rb-4.1.0&q=80&w=1080",
      "imageHint": "auto deportivo rojo",
      "width": 1200,
      "height": 800
    },
    {
      "id": "aurora-gt",
      "description": "Un auto deportivo en una carretera sinuosa.",
      "imageUrl": "https://images.unsplash.com/photo-1506610654-064fbba4780c?crop=entropy&cs=tinysrgb&fit=max&fm=jpg&ixid=M3w3NDE5ODJ8MHwxfHNlYXJjaHw5fHxhdXRvJTIwZGVwb3J0aXZvfGVufDB8fHx8MTc2Mjg5NDQyNHww&ixlib=rb-4.1.0&q=80&w=1080",
      "imageHint": "auto deportivo",
      "width": 1200,
      "height": 800
    },
    {
      "id": "volta-ev-pro",
      "description": "Un auto eléctrico cargando en un garaje futurista.",
      "imageUrl": "https://images.unsplash.com/photo-1577861641567-d42d659b95a4?crop=entropy&cs=tinysrgb&fit=max&fm=jpg&ixid=M3w3NDE5ODJ8MHwxfHNlYXJjaHw2fHxhdXRvJTIwZWwlQzMlQTljdHJpY298ZW58MHx8fHwxNzYyODk0NDI1fDA&ixlib=rb-4.1.0&q=80&w=1080",
      "imageHint": "auto eléctrico",
      "width": 800,
      "height": 600
    },
    {
      "id": "horizon-suv",
      "description": "Un SUV estacionado con vista a la montaña de fondo.",
      "imageUrl": "https://images.unsplash.com/photo-1659935405041-1e76d8bd9de6?crop=entropy&cs=tinysrgb&fit=max&fm=jpg&ixid=M3w3NDE5ODJ8MHwxfHNlYXJjaHwxfHxzdXYlMjBtb250YSVDMyVCMWFzfGVufDB8fHx8MTc2Mjg5NDQyNXww&ixlib=rb-4.1.0&q=80&w=1080",
      "imageHint": "suv montañas",
      "width": 800,
      "height": 600
    },
    {
      "id": "nomad-cruiser",
      "description": "Un sedán cómodo en una calle suburbana.",
      "imageUrl": "https://picsum.photos/seed/nomad-cruiser/800/600",
      "imageHint": "sedán familiar",
      "width": 800,
      "height": 600
    },
    {
      "id": "comet-r",
      "description": "Un auto deportivo compacto en una pista de carreras.",
      "imageUrl": "https://images.unsplash.com/photo-1714622857097-7f0f7f29d305?crop=entropy&cs=tinysrgb&fit=max&fm=jpg&ixid=M3w3NDE5ODJ8MHwxfHNlYXJjaHwyfHxoYXRjaGJhY2slMjBkZXBvcnRpdm98ZW58MHx8fHwxNzYyODk0NDI0fDA&ixlib=rb-4.1.0&q=80&w=1080",
      "imageHint": "hatchback deportivo",
      "width": 800,
      "height": 600
    },
    {
      "id": "stratus-sedan",
      "description": "Un sedán híbrido conduciendo por un paisaje verde.",
      "imageUrl": "https://images.unsplash.com/photo-1750493601689-30a06059092a?crop=entropy&cs=tinysrgb&fit=max&fm=jpg&ixid=M3w3NDE5ODJ8MHwxfHNlYXJjaHw1fHxhdXRvJTIwaCVDMyVBRGJyaWRvfGVufDB8fHx8MTc2Mjg5NDQyNXww&ixlib=rb-4.1.0&q=80&w=1080",
      "imageHint": "auto híbrido",
      "width": 800,
      "height": 600
    },
    {
      "id": "terra-truck",
      "description": "Una camioneta en un camino de tierra en el desierto.",
      "imageUrl": "https://images.unsplash.com/photo-1629418010472-ffdd0108571b?crop=entropy&cs=tinysrgb&fit=max&fm=jpg&ixid=M3w3NDE5ODJ8MHwxfHNlYXJjaHwzfHxjYW1pb25ldGElMjBwaWNrdXB8ZW58MHx8fHwxNzYyODk0NDI0fDA&ixlib=rb-4.1.0&q=80&w=1080",
      "imageHint": "camioneta pickup",
      "width": 800,
      "height": 600
    }
  ]
}